goblinoid/__init__.py
goblinoid/cli.py
goblinoid/create.py
goblinoid/exceptions.py
goblinoid/utils.py
goblinoid-0.0.0.dist-info/METADATA
goblinoid-0.0.0.dist-info/RECORD
goblinoid-0.0.0.dist-info/WHEEL
goblinoid-0.0.0.dist-info/entry_points.txt
goblinoid-0.0.0.dist-info/top_level.txt
