Metadata-Version: 2.1
Name: goblinoid
Version: 0.0.0
Summary: Create a graph database schema and indexes from source code automatically
Home-page: https://github.com/fridex/goblinoid
Author: Fridolin Pokorny
Author-email: fridolin.pokorny@gmail.com
Maintainer: Fridolin Pokorny
Maintainer-email: fridolin.pokorny@gmail.com
License: GPLv2
Keywords: graph graph-database graph-db janusgraph tinkerpop gremlin gremlin-server
Platform: UNKNOWN
Classifier: Development Status :: 4 - Beta
Classifier: Environment :: Console
Classifier: Intended Audience :: Developers
Classifier: Intended Audience :: End Users/Desktop
Classifier: License :: OSI Approved :: GNU General Public License v2 (GPLv2)
Classifier: Operating System :: OS Independent
Classifier: Programming Language :: Python :: 3
Classifier: Programming Language :: Python :: 3.6
Classifier: Programming Language :: Python :: 3.7
Classifier: Programming Language :: Python :: 3 :: Only
Classifier: Programming Language :: Python :: Implementation :: CPython
Classifier: Programming Language :: Python :: Implementation :: PyPy
Classifier: Topic :: Database
Classifier: Topic :: Utilities
Requires-Dist: goblin
Requires-Dist: click
Requires-Dist: daiquiri
